lost_cat_office/__init__.py
lost_cat_office/examples/run_azurescan.py
lost_cat_office/parsers/__init__.py
lost_cat_office/parsers/pdf_parser.py
lost_cat_office/parsers/word_parser.py
lost_cat_office/processors/__init__.py
lost_cat_office/processors/azureblob_processor.py
lost_cat_office/processors/word_processor.py
lost_cat_office/utils/__init__.py
lost_cat_office-0.0.4.dist-info/LICENSE
lost_cat_office-0.0.4.dist-info/METADATA
lost_cat_office-0.0.4.dist-info/WHEEL
lost_cat_office-0.0.4.dist-info/top_level.txt
lost_cat_office-0.0.4.dist-info/RECORD
