Metadata-Version: 2.1
Name: lost-cat-office
Version: 0.0.4
Summary: Lost cat Office is a package containing office document parsers
Author-email: Dreffed aka David Gloyn-Cox <dreffed@gmail.com>, Thoughtswin Systems Inc <david.gloyn-cox@thoughtswinsystems.com>
License: MIT License
Project-URL: Homepage, https://github.com/thoughtswinsystems/lost_cat_office
Project-URL: Bug Tracker, https://github.com/thoughtswinsystems/lost_cat_office/issues
Classifier: Programming Language :: Python :: 3
Classifier: License :: OSI Approved :: MIT License
Classifier: Operating System :: OS Independent
Requires-Python: >=3.8
License-File: LICENSE
Requires-Dist: lost-cat
Requires-Dist: psutil
Requires-Dist: pillow
Requires-Dist: pymupdf
Requires-Dist: python-docx
Requires-Dist: docx2txt
Requires-Dist: azure-storage-blob
